README.md
git_labeler/script.py
git_labeler-0.1.2.dist-info/entry_points.txt
git_labeler-0.1.2.dist-info/LICENSE.txt
git_labeler-0.1.2.dist-info/WHEEL
git_labeler-0.1.2.dist-info/METADATA
git_labeler-0.1.2.dist-info/RECORD
