Metadata-Version: 2.1
Name: git-labeler
Version: 0.1.2
Summary: Apply, change, remove labels on multiple or single repos in one go
Home-page: https://stiliajohny.github.io/python-git-labeler 
License: GPL-3
Keywords: git,multi-label,label,automation,github, github-api
Author: John Stilia
Author-email: stilia.johny@gmail.com
Requires-Python: >=3.10,<4.0
Classifier: License :: Other/Proprietary License
Classifier: Programming Language :: Python :: 3
Classifier: Programming Language :: Python :: 3.10
Requires-Dist: GitPython (>=3.1.27,<4.0.0)
Requires-Dist: pyaml (>=21.10.1,<22.0.0)
Requires-Dist: pyfiglet (>=0.8.post1,<0.9)
Requires-Dist: requests (>=2.27.1,<3.0.0)
Project-URL: Repository, https://github.com/stiliajohny/python-git-labeler.git 
